README.md
setup.py
console_alarm/__init__.py
console_alarm/command_line.py
console_alarm/console_alarm.py
console_alarm.egg-info/PKG-INFO
console_alarm.egg-info/SOURCES.txt
console_alarm.egg-info/dependency_links.txt
console_alarm.egg-info/entry_points.txt
console_alarm.egg-info/requires.txt
console_alarm.egg-info/top_level.txt